LICENSE
MANIFEST.in
README.rst
setup.py
tests.py
hotqueue/__init__.py
hotqueue/hotqueue.py
hotqueue/package_metadata.json
redislite_hotqueue.egg-info/PKG-INFO
redislite_hotqueue.egg-info/SOURCES.txt
redislite_hotqueue.egg-info/dependency_links.txt
redislite_hotqueue.egg-info/requires.txt
redislite_hotqueue.egg-info/top_level.txt