Metadata-Version: 1.1
Name: redislite-hotqueue
Version: 1.3.83
Summary: A fork of the HotQueue Python library that allows you to use Redis/Redislite as a message queue.
Home-page: http://github.com/dwighthubbard/hotqueue
Author: Dwight Hubbard
Author-email: d@d-h.us
License: MIT
Platform: UNKNOWN
Classifier: Programming Language :: Python
Classifier: Development Status :: 4 - Beta
Classifier: Intended Audience :: Developers
Classifier: License :: OSI Approved :: MIT License
Classifier: Operating System :: OS Independent
Classifier: Topic :: Software Development :: Libraries :: Python Modules
